codeinterpreterapi/__init__.py
codeinterpreterapi/config.py
codeinterpreterapi/session.py
codeinterpreterapi/agents/__init__.py
codeinterpreterapi/agents/custom_agent.py
codeinterpreterapi/agents/functions_agent.py
codeinterpreterapi/chains/__init__.py
codeinterpreterapi/chains/extract_code.py
codeinterpreterapi/chains/modifications_check.py
codeinterpreterapi/chains/rm_dl_link.py
codeinterpreterapi/prompts/__init__.py
codeinterpreterapi/prompts/modifications_check.py
codeinterpreterapi/prompts/remove_dl_link.py
codeinterpreterapi/prompts/system_message.py
codeinterpreterapi/schema/__init__.py
codeinterpreterapi/schema/file.py
codeinterpreterapi/schema/input.py
codeinterpreterapi/schema/response.py
codeinterpreterapi/utils/__init__.py
codeinterpreterapi/utils/callbacks.py
codeinterpreterapi/utils/parser.py
frontend/__init__.py
frontend/app.py
frontend/utils.py
codeinterpreterapi_warren-0.1.0.dist-info/LICENSE
codeinterpreterapi_warren-0.1.0.dist-info/METADATA
codeinterpreterapi_warren-0.1.0.dist-info/WHEEL
codeinterpreterapi_warren-0.1.0.dist-info/top_level.txt
codeinterpreterapi_warren-0.1.0.dist-info/RECORD
