Metadata-Version: 2.1
Name: codeinterpreterapi-warren
Version: 0.1.0
Summary: Fork of https://github.com/shroominic/codeinterpreter-api
Home-page: https://github.com/somethingwentwell/codeinterpreter-api
Author: Warren Wong
Author-email: wwwc@outlook.com
Classifier: Development Status :: 3 - Alpha
Classifier: License :: OSI Approved :: MIT License
Classifier: Programming Language :: Python :: 3
Classifier: Programming Language :: Python :: 3.6
Classifier: Programming Language :: Python :: 3.7
Classifier: Programming Language :: Python :: 3.8
Classifier: Programming Language :: Python :: 3.9
Classifier: Programming Language :: Python :: 3 :: Only
License-File: LICENSE
